{"match_id":"NOR_ENG","home_team":"Norway","away_team":"England","result":{"home_goals":1,"away_goals":2,"status_short":"AET","finished_at":"2026-07-11T23:47:54.850288","goals":[{"team":"home","player":"Andreas Schjelderup","minute":36,"detail":"Goal"},{"team":"away","player":"Jude Bellingham","minute":47,"detail":"Goal"},{"team":"away","player":"Jude Bellingham","minute":93,"detail":"Goal"}]},"final_lock":[{"market_id":"KXWCADVANCE-26JUL11NORENG-ENG","market_title":"England to advance","outcome_key":"away_advance","model_probability":0.60398,"kalshi_odds":1.47,"implied_probability":0.68,"edge":-0.07602000000000009,"confidence":0.4705,"locked_at":"2026-07-11T20:50:31.578533"},{"market_id":"KXWCADVANCE-26JUL11NORENG-NOR","market_title":"Norway to advance","outcome_key":"home_advance","model_probability":0.40002,"kalshi_odds":3.03,"implied_probability":0.33,"edge":0.07001999999999997,"confidence":0.4705,"locked_at":"2026-07-11T20:50:31.578532"},{"market_id":"KXWCFTTS-26JUL11NORENG-ENG","market_title":"England to score first","outcome_key":"away_first_goal","model_probability":0.54392,"kalshi_odds":1.69,"implied_probability":0.59,"edge":-0.04608000000000001,"confidence":0.4705,"locked_at":"2026-07-11T20:50:31.578532"},{"market_id":"KXWCFTTS-26JUL11NORENG-NONE","market_title":"No goal in the match","outcome_key":"no_goal","model_probability":0.03382,"kalshi_odds":25.0,"implied_probability":0.04,"edge":-0.006179999999999998,"confidence":0.4705,"locked_at":"2026-07-11T20:50:31.578532"},{"market_id":"KXWCFTTS-26JUL11NORENG-NOR","market_title":"Norway to score first","outcome_key":"home_first_goal","model_probability":0.43026000000000003,"kalshi_odds":2.56,"implied_probability":0.39,"edge":0.04026000000000002,"confidence":0.4705,"locked_at":"2026-07-11T20:50:31.578531"},{"market_id":"KXWCSCORE-26JUL11NORENG-NOR0ENG0","market_title":"Exact score: 0-0 draw","outcome_key":"score_0_0","model_probability":0.04206,"kalshi_odds":16.67,"implied_probability":0.06,"edge":-0.017939999999999998,"confidence":0.4705,"locked_at":"2026-07-11T20:50:31.578531"},{"market_id":"KXWCSCORE-26JUL11NORENG-NOR0ENG1","market_title":"Exact score: England 1-0 Norway","outcome_key":"score_0_1","model_probability":0.07270000000000001,"kalshi_odds":10.0,"implied_probability":0.1,"edge":-0.02729999999999999,"confidence":0.4705,"locked_at":"2026-07-11T20:50:31.578531"},{"market_id":"KXWCSCORE-26JUL11NORENG-NOR0ENG2","market_title":"Exact score: England 2-0 Norway","outcome_key":"score_0_2","model_probability":0.06624,"kalshi_odds":11.11,"implied_probability":0.09,"edge":-0.023760000000000003,"confidence":0.4705,"locked_at":"2026-07-11T20:50:31.578530"},{"market_id":"KXWCSCORE-26JUL11NORENG-NOR0ENG3","market_title":"Exact score: England 3-0 Norway","outcome_key":"score_0_3","model_probability":0.04046,"kalshi_odds":20.0,"implied_probability":0.05,"edge":-0.00954,"confidence":0.4705,"locked_at":"2026-07-11T20:50:31.578530"},{"market_id":"KXWCSCORE-26JUL11NORENG-NOR0ENG4","market_title":"Exact score: England 4-0 Norway","outcome_key":"score_0_4","model_probability":0.01574,"kalshi_odds":50.0,"implied_probability":0.02,"edge":-0.00426,"confidence":0.4705,"locked_at":"2026-07-11T20:50:31.578529"},{"market_id":"KXWCSCORE-26JUL11NORENG-NOR0ENG5","market_title":"Exact score: England 5-0 Norway","outcome_key":"score_0_5","model_probability":0.006699999999999999,"kalshi_odds":100.0,"implied_probability":0.01,"edge":-0.003300000000000001,"confidence":0.4705,"locked_at":"2026-07-11T20:50:31.578529"},{"market_id":"KXWCSCORE-26JUL11NORENG-NOR1ENG0","market_title":"Exact score: Norway 1-0 England","outcome_key":"score_1_0","model_probability":0.0525,"kalshi_odds":16.67,"implied_probability":0.06,"edge":-0.0075,"confidence":0.4705,"locked_at":"2026-07-11T20:50:31.578529"},{"market_id":"KXWCSCORE-26JUL11NORENG-NOR1ENG1","market_title":"Exact score: 1-1 draw","outcome_key":"score_1_1","model_probability":0.10152,"kalshi_odds":8.33,"implied_probability":0.12,"edge":-0.018479999999999996,"confidence":0.4705,"locked_at":"2026-07-11T20:50:31.578528"},{"market_id":"KXWCSCORE-26JUL11NORENG-NOR1ENG2","market_title":"Exact score: England 2-1 Norway","outcome_key":"score_1_2","model_probability":0.1024,"kalshi_odds":7.69,"implied_probability":0.13,"edge":-0.0276,"confidence":0.4705,"locked_at":"2026-07-11T20:50:31.578528"},{"market_id":"KXWCSCORE-26JUL11NORENG-NOR1ENG3","market_title":"Exact score: England 3-1 Norway","outcome_key":"score_1_3","model_probability":0.06094,"kalshi_odds":14.29,"implied_probability":0.07,"edge":-0.009060000000000006,"confidence":0.4705,"locked_at":"2026-07-11T20:50:31.578527"},{"market_id":"KXWCSCORE-26JUL11NORENG-NOR1ENG4","market_title":"Exact score: England 4-1 Norway","outcome_key":"score_1_4","model_probability":0.02724,"kalshi_odds":33.33,"implied_probability":0.03,"edge":-0.0027599999999999986,"confidence":0.4705,"locked_at":"2026-07-11T20:50:31.578527"},{"market_id":"KXWCSCORE-26JUL11NORENG-NOR1ENG5","market_title":"Exact score: England 5-1 Norway","outcome_key":"score_1_5","model_probability":0.0097,"kalshi_odds":100.0,"implied_probability":0.01,"edge":-0.0002999999999999999,"confidence":0.4705,"locked_at":"2026-07-11T20:50:31.578527"},{"market_id":"KXWCSCORE-26JUL11NORENG-NOR2ENG0","market_title":"Exact score: Norway 2-0 England","outcome_key":"score_2_0","model_probability":0.04126,"kalshi_odds":25.0,"implied_probability":0.04,"edge":0.0012599999999999972,"confidence":0.4705,"locked_at":"2026-07-11T20:50:31.578526"},{"market_id":"KXWCSCORE-26JUL11NORENG-NOR2ENG1","market_title":"Exact score: Norway 2-1 England","outcome_key":"score_2_1","model_probability":0.07400000000000001,"kalshi_odds":12.5,"implied_probability":0.08,"edge":-0.0059999999999999915,"confidence":0.4705,"locked_at":"2026-07-11T20:50:31.578526"},{"market_id":"KXWCSCORE-26JUL11NORENG-NOR2ENG2","market_title":"Exact score: 2-2 draw","outcome_key":"score_2_2","model_probability":0.06831999999999999,"kalshi_odds":14.29,"implied_probability":0.07,"edge":-0.0016800000000000148,"confidence":0.4705,"locked_at":"2026-07-11T20:50:31.578526"},{"market_id":"KXWCSCORE-26JUL11NORENG-NOR2ENG3","market_title":"Exact score: England 3-2 Norway","outcome_key":"score_2_3","model_probability":0.045500000000000006,"kalshi_odds":20.0,"implied_probability":0.05,"edge":-0.004499999999999997,"confidence":0.4705,"locked_at":"2026-07-11T20:50:31.578525"},{"market_id":"KXWCSCORE-26JUL11NORENG-NOR2ENG4","market_title":"Exact score: England 4-2 Norway","outcome_key":"score_2_4","model_probability":0.019459999999999998,"kalshi_odds":50.0,"implied_probability":0.02,"edge":-0.0005400000000000023,"confidence":0.4705,"locked_at":"2026-07-11T20:50:31.578525"},{"market_id":"KXWCSCORE-26JUL11NORENG-NOR2ENG5","market_title":"Exact score: England 5-2 Norway","outcome_key":"score_2_5","model_probability":0.01012,"kalshi_odds":100.0,"implied_probability":0.01,"edge":0.00012000000000000031,"confidence":0.4705,"locked_at":"2026-07-11T20:50:31.578524"},{"market_id":"KXWCSCORE-26JUL11NORENG-NOR3ENG0","market_title":"Exact score: Norway 3-0 England","outcome_key":"score_3_0","model_probability":0.01774,"kalshi_odds":100.0,"implied_probability":0.01,"edge":0.007739999999999999,"confidence":0.4705,"locked_at":"2026-07-11T20:50:31.578524"},{"market_id":"KXWCSCORE-26JUL11NORENG-NOR3ENG1","market_title":"Exact score: Norway 3-1 England","outcome_key":"score_3_1","model_probability":0.03966,"kalshi_odds":33.33,"implied_probability":0.03,"edge":0.009660000000000002,"confidence":0.4705,"locked_at":"2026-07-11T20:50:31.578523"},{"market_id":"KXWCSCORE-26JUL11NORENG-NOR3ENG2","market_title":"Exact score: Norway 3-2 England","outcome_key":"score_3_2","model_probability":0.03522,"kalshi_odds":33.33,"implied_probability":0.03,"edge":0.005220000000000002,"confidence":0.4705,"locked_at":"2026-07-11T20:50:31.578523"},{"market_id":"KXWCSCORE-26JUL11NORENG-NOR3ENG3","market_title":"Exact score: 3-3 draw","outcome_key":"score_3_3","model_probability":0.02234,"kalshi_odds":50.0,"implied_probability":0.02,"edge":0.0023399999999999983,"confidence":0.4705,"locked_at":"2026-07-11T20:50:31.578523"},{"market_id":"KXWCSCORE-26JUL11NORENG-NOR3ENG4","market_title":"Exact score: England 4-3 Norway","outcome_key":"score_3_4","model_probability":0.0112,"kalshi_odds":100.0,"implied_probability":0.01,"edge":0.0011999999999999997,"confidence":0.4705,"locked_at":"2026-07-11T20:50:31.578522"},{"market_id":"KXWCSCORE-26JUL11NORENG-NOR4ENG0","market_title":"Exact score: Norway 4-0 England","outcome_key":"score_4_0","model_probability":0.0097,"kalshi_odds":100.0,"implied_probability":0.01,"edge":-0.0002999999999999999,"confidence":0.4705,"locked_at":"2026-07-11T20:50:31.578522"},{"market_id":"KXWCSCORE-26JUL11NORENG-NOR4ENG1","market_title":"Exact score: Norway 4-1 England","outcome_key":"score_4_1","model_probability":0.014920000000000001,"kalshi_odds":100.0,"implied_probability":0.01,"edge":0.004920000000000001,"confidence":0.4705,"locked_at":"2026-07-11T20:50:31.578521"},{"market_id":"KXWCSCORE-26JUL11NORENG-NOR4ENG2","market_title":"Exact score: Norway 4-2 England","outcome_key":"score_4_2","model_probability":0.01282,"kalshi_odds":100.0,"implied_probability":0.01,"edge":0.0028199999999999996,"confidence":0.4705,"locked_at":"2026-07-11T20:50:31.578521"},{"market_id":"KXWCSCORE-26JUL11NORENG-NOR4ENG3","market_title":"Exact score: Norway 4-3 England","outcome_key":"score_4_3","model_probability":0.01126,"kalshi_odds":100.0,"implied_probability":0.01,"edge":0.001259999999999999,"confidence":0.4705,"locked_at":"2026-07-11T20:50:31.578521"},{"market_id":"KXWCBTTS-26JUL11NORENG-BTTS","market_title":"Both teams to score","outcome_key":"btts","model_probability":0.66718,"kalshi_odds":1.56,"implied_probability":0.64,"edge":0.027179999999999982,"confidence":0.4705,"locked_at":"2026-07-11T20:50:31.578520"},{"market_id":"KXWCSPREAD-26JUL11NORENG-ENG2","market_title":"England to win by 2+ goals","outcome_key":"away_margin_2","model_probability":0.264,"kalshi_odds":3.33,"implied_probability":0.3,"edge":-0.035999999999999976,"confidence":0.4705,"locked_at":"2026-07-11T20:50:31.578520"},{"market_id":"KXWCSPREAD-26JUL11NORENG-ENG3","market_title":"England to win by 3+ goals","outcome_key":"away_margin_3","model_probability":0.11394,"kalshi_odds":8.33,"implied_probability":0.12,"edge":-0.006059999999999996,"confidence":0.4705,"locked_at":"2026-07-11T20:50:31.578519"},{"market_id":"KXWCSPREAD-26JUL11NORENG-NOR2","market_title":"Norway to win by 2+ goals","outcome_key":"home_margin_2","model_probability":0.13951999999999998,"kalshi_odds":12.5,"implied_probability":0.08,"edge":0.059519999999999976,"confidence":0.4705,"locked_at":"2026-07-11T20:50:31.578519"},{"market_id":"KXWCSPREAD-26JUL11NORENG-NOR3","market_title":"Norway to win by 3+ goals","outcome_key":"home_margin_3","model_probability":0.05144,"kalshi_odds":50.0,"implied_probability":0.02,"edge":0.031439999999999996,"confidence":0.4705,"locked_at":"2026-07-11T20:50:31.578519"},{"market_id":"KXWCTOTAL-26JUL11NORENG-1","market_title":"Over 0.5 total goals","outcome_key":"over_0_5","model_probability":0.96194,"kalshi_odds":1.05,"implied_probability":0.95,"edge":0.011940000000000062,"confidence":0.4705,"locked_at":"2026-07-11T20:50:31.578518"},{"market_id":"KXWCTOTAL-26JUL11NORENG-2","market_title":"Over 1.5 total goals","outcome_key":"over_1_5","model_probability":0.84074,"kalshi_odds":1.25,"implied_probability":0.8,"edge":0.04074,"confidence":0.4705,"locked_at":"2026-07-11T20:50:31.578518"},{"market_id":"KXWCTOTAL-26JUL11NORENG-3","market_title":"Over 2.5 total goals","outcome_key":"over_2_5","model_probability":0.6397200000000001,"kalshi_odds":1.75,"implied_probability":0.57,"edge":0.06972000000000012,"confidence":0.4705,"locked_at":"2026-07-11T20:50:31.578517"},{"market_id":"KXWCTOTAL-26JUL11NORENG-4","market_title":"Over 3.5 total goals","outcome_key":"over_3_5","model_probability":0.41712,"kalshi_odds":3.03,"implied_probability":0.33,"edge":0.08711999999999998,"confidence":0.4705,"locked_at":"2026-07-11T20:50:31.578517"},{"market_id":"KXWCTOTAL-26JUL11NORENG-5","market_title":"Over 4.5 total goals","outcome_key":"over_4_5","model_probability":0.24275999999999998,"kalshi_odds":5.56,"implied_probability":0.18,"edge":0.06275999999999998,"confidence":0.4705,"locked_at":"2026-07-11T20:50:31.578517"},{"market_id":"KXWCTOTAL-26JUL11NORENG-6","market_title":"Over 5.5 total goals","outcome_key":"over_5_5","model_probability":0.12362,"kalshi_odds":12.5,"implied_probability":0.08,"edge":0.04361999999999999,"confidence":0.4705,"locked_at":"2026-07-11T20:50:31.578516"},{"market_id":"KXWCGAME-26JUL11NORENG-TIE","market_title":"Draw after 90 min","outcome_key":"draw","model_probability":0.22924,"kalshi_odds":4.0,"implied_probability":0.25,"edge":-0.02076,"confidence":0.4705,"locked_at":"2026-07-11T20:50:31.578516"},{"market_id":"KXWCMOV-26JUL11NORENG-ENGET","market_title":"England to win in extra time","outcome_key":"away_win_et","model_probability":0.07232,"kalshi_odds":12.5,"implied_probability":0.08,"edge":-0.007680000000000006,"confidence":0.4705,"locked_at":"2026-07-11T20:50:31.578515"},{"market_id":"KXWCMOV-26JUL11NORENG-ENGPEN","market_title":"England to win on penalties","outcome_key":"away_win_pens","model_probability":0.06254,"kalshi_odds":12.5,"implied_probability":0.08,"edge":-0.017460000000000003,"confidence":0.4705,"locked_at":"2026-07-11T20:50:31.578515"},{"market_id":"KXWCMOV-26JUL11NORENG-ENGREG","market_title":"England to win (90 min)","outcome_key":"away_win","model_probability":0.47312,"kalshi_odds":1.89,"implied_probability":0.53,"edge":-0.05688000000000004,"confidence":0.4705,"locked_at":"2026-07-11T20:50:31.578514"},{"market_id":"KXWCMOV-26JUL11NORENG-NORET","market_title":"Norway to win in extra time","outcome_key":"home_win_et","model_probability":0.05712,"kalshi_odds":16.67,"implied_probability":0.06,"edge":-0.0028800000000000006,"confidence":0.4705,"locked_at":"2026-07-11T20:50:31.578514"},{"market_id":"KXWCMOV-26JUL11NORENG-NORPEN","market_title":"Norway to win on penalties","outcome_key":"home_win_pens","model_probability":0.05326,"kalshi_odds":14.29,"implied_probability":0.07,"edge":-0.016740000000000005,"confidence":0.4705,"locked_at":"2026-07-11T20:50:31.578513"},{"market_id":"KXWCGAME-26JUL11NORENG-NOR","market_title":"Norway to win (90 min)","outcome_key":"home_win","model_probability":0.30164,"kalshi_odds":4.35,"implied_probability":0.23,"edge":0.07164000000000001,"confidence":0.4705,"locked_at":"2026-07-11T20:50:31.578508"}],"closing":[{"market_id":"KXWCADVANCE-26JUL11NORENG-ENG","event_ticker":"KXWCADVANCE-26JUL11NORENG","captured_at":"2026-07-11T23:47:54.855364","title":"Norway vs England: To Advance","status":"active","result":"","yes_bid":"0.9900","yes_ask":"1.0000","last_price":"0.9900","volume":null,"open_interest":null},{"market_id":"KXWCADVANCE-26JUL11NORENG-NOR","event_ticker":"KXWCADVANCE-26JUL11NORENG","captured_at":"2026-07-11T23:47:54.855364","title":"Norway vs England: To Advance","status":"active","result":"","yes_bid":"0.0000","yes_ask":"0.0100","last_price":"0.0100","volume":null,"open_interest":null},{"market_id":"KXWCBTTS-26JUL11NORENG-BTTS","event_ticker":"KXWCBTTS-26JUL11NORENG","captured_at":"2026-07-11T23:47:54.855364","title":"Will both teams score?","status":"finalized","result":"yes","yes_bid":"0.0000","yes_ask":"1.0000","last_price":"0.9900","volume":null,"open_interest":null},{"market_id":"KXWCFTTS-26JUL11NORENG-ENG","event_ticker":"KXWCFTTS-26JUL11NORENG","captured_at":"2026-07-11T23:47:54.855364","title":"Will England record the first goal of the game?","status":"finalized","result":"no","yes_bid":"0.0000","yes_ask":"1.0000","last_price":"0.0100","volume":null,"open_interest":null},{"market_id":"KXWCFTTS-26JUL11NORENG-NONE","event_ticker":"KXWCFTTS-26JUL11NORENG","captured_at":"2026-07-11T23:47:54.855364","title":"Will no goal be scored?","status":"finalized","result":"no","yes_bid":"0.0000","yes_ask":"1.0000","last_price":"0.0100","volume":null,"open_interest":null},{"market_id":"KXWCFTTS-26JUL11NORENG-NOR","event_ticker":"KXWCFTTS-26JUL11NORENG","captured_at":"2026-07-11T23:47:54.855364","title":"Will Norway record the first goal of the game?","status":"finalized","result":"yes","yes_bid":"0.0000","yes_ask":"1.0000","last_price":"0.9900","volume":null,"open_interest":null},{"market_id":"KXWCGAME-26JUL11NORENG-ENG","event_ticker":"KXWCGAME-26JUL11NORENG","captured_at":"2026-07-11T23:47:54.855364","title":"Norway vs England Winner?","status":"finalized","result":"no","yes_bid":"0.0000","yes_ask":"1.0000","last_price":"0.0100","volume":null,"open_interest":null},{"market_id":"KXWCGAME-26JUL11NORENG-NOR","event_ticker":"KXWCGAME-26JUL11NORENG","captured_at":"2026-07-11T23:47:54.855364","title":"Norway vs England Winner?","status":"finalized","result":"no","yes_bid":"0.0000","yes_ask":"1.0000","last_price":"0.0100","volume":null,"open_interest":null},{"market_id":"KXWCGAME-26JUL11NORENG-TIE","event_ticker":"KXWCGAME-26JUL11NORENG","captured_at":"2026-07-11T23:47:54.855364","title":"Norway vs England Winner?","status":"finalized","result":"yes","yes_bid":"0.0000","yes_ask":"1.0000","last_price":"0.9900","volume":null,"open_interest":null},{"market_id":"KXWCMOV-26JUL11NORENG-ENGET","event_ticker":"KXWCMOV-26JUL11NORENG","captured_at":"2026-07-11T23:47:54.855364","title":"Will England win in Extra Time?","status":"active","result":"","yes_bid":"0.9900","yes_ask":"1.0000","last_price":"0.9900","volume":null,"open_interest":null},{"market_id":"KXWCMOV-26JUL11NORENG-ENGPEN","event_ticker":"KXWCMOV-26JUL11NORENG","captured_at":"2026-07-11T23:47:54.855364","title":"Will England win in Penalty Shootout?","status":"active","result":"","yes_bid":"0.0000","yes_ask":"0.0100","last_price":"0.0100","volume":null,"open_interest":null},{"market_id":"KXWCMOV-26JUL11NORENG-ENGREG","event_ticker":"KXWCMOV-26JUL11NORENG","captured_at":"2026-07-11T23:47:54.855364","title":"Will England win in Regulation Time?","status":"finalized","result":"no","yes_bid":"0.0000","yes_ask":"1.0000","last_price":"0.0100","volume":null,"open_interest":null},{"market_id":"KXWCMOV-26JUL11NORENG-NORET","event_ticker":"KXWCMOV-26JUL11NORENG","captured_at":"2026-07-11T23:47:54.855364","title":"Will Norway win in Extra Time?","status":"active","result":"","yes_bid":"0.0000","yes_ask":"0.0100","last_price":"0.0100","volume":null,"open_interest":null},{"market_id":"KXWCMOV-26JUL11NORENG-NORPEN","event_ticker":"KXWCMOV-26JUL11NORENG","captured_at":"2026-07-11T23:47:54.855364","title":"Will Norway win in Penalty Shootout?","status":"active","result":"","yes_bid":"0.0000","yes_ask":"0.0100","last_price":"0.0100","volume":null,"open_interest":null},{"market_id":"KXWCMOV-26JUL11NORENG-NORREG","event_ticker":"KXWCMOV-26JUL11NORENG","captured_at":"2026-07-11T23:47:54.855364","title":"Will Norway win in Regulation Time?","status":"finalized","result":"no","yes_bid":"0.0000","yes_ask":"1.0000","last_price":"0.0100","volume":null,"open_interest":null},{"market_id":"KXWCSCORE-26JUL11NORENG-NOR0ENG0","event_ticker":"KXWCSCORE-26JUL11NORENG","captured_at":"2026-07-11T23:47:54.855364","title":"Will the final score be Draw 0-0?","status":"finalized","result":"no","yes_bid":"0.0000","yes_ask":"1.0000","last_price":"0.0100","volume":null,"open_interest":null},{"market_id":"KXWCSCORE-26JUL11NORENG-NOR0ENG1","event_ticker":"KXWCSCORE-26JUL11NORENG","captured_at":"2026-07-11T23:47:54.855364","title":"Will the final score be England wins 1-0?","status":"finalized","result":"no","yes_bid":"0.0000","yes_ask":"1.0000","last_price":"0.0100","volume":null,"open_interest":null},{"market_id":"KXWCSCORE-26JUL11NORENG-NOR0ENG2","event_ticker":"KXWCSCORE-26JUL11NORENG","captured_at":"2026-07-11T23:47:54.855364","title":"Will the final score be England wins 2-0?","status":"finalized","result":"no","yes_bid":"0.0000","yes_ask":"1.0000","last_price":"0.0100","volume":null,"open_interest":null},{"market_id":"KXWCSCORE-26JUL11NORENG-NOR0ENG3","event_ticker":"KXWCSCORE-26JUL11NORENG","captured_at":"2026-07-11T23:47:54.855364","title":"Will the final score be England wins 3-0?","status":"finalized","result":"no","yes_bid":"0.0000","yes_ask":"1.0000","last_price":"0.0100","volume":null,"open_interest":null},{"market_id":"KXWCSCORE-26JUL11NORENG-NOR0ENG4","event_ticker":"KXWCSCORE-26JUL11NORENG","captured_at":"2026-07-11T23:47:54.855364","title":"Will the final score be England wins 4-0?","status":"finalized","result":"no","yes_bid":"0.0000","yes_ask":"1.0000","last_price":"0.0100","volume":null,"open_interest":null},{"market_id":"KXWCSCORE-26JUL11NORENG-NOR0ENG5","event_ticker":"KXWCSCORE-26JUL11NORENG","captured_at":"2026-07-11T23:47:54.855364","title":"Will the final score be England wins 5-0?","status":"finalized","result":"no","yes_bid":"0.0000","yes_ask":"1.0000","last_price":"0.0100","volume":null,"open_interest":null},{"market_id":"KXWCSCORE-26JUL11NORENG-NOR1ENG0","event_ticker":"KXWCSCORE-26JUL11NORENG","captured_at":"2026-07-11T23:47:54.855364","title":"Will the final score be Norway wins 1-0?","status":"finalized","result":"no","yes_bid":"0.0000","yes_ask":"1.0000","last_price":"0.0100","volume":null,"open_interest":null},{"market_id":"KXWCSCORE-26JUL11NORENG-NOR1ENG1","event_ticker":"KXWCSCORE-26JUL11NORENG","captured_at":"2026-07-11T23:47:54.855364","title":"Will the final score be Draw 1-1?","status":"finalized","result":"yes","yes_bid":"0.0000","yes_ask":"1.0000","last_price":"0.9900","volume":null,"open_interest":null},{"market_id":"KXWCSCORE-26JUL11NORENG-NOR1ENG2","event_ticker":"KXWCSCORE-26JUL11NORENG","captured_at":"2026-07-11T23:47:54.855364","title":"Will the final score be England wins 2-1?","status":"finalized","result":"no","yes_bid":"0.0000","yes_ask":"1.0000","last_price":"0.0100","volume":null,"open_interest":null},{"market_id":"KXWCSCORE-26JUL11NORENG-NOR1ENG3","event_ticker":"KXWCSCORE-26JUL11NORENG","captured_at":"2026-07-11T23:47:54.855364","title":"Will the final score be England wins 3-1?","status":"finalized","result":"no","yes_bid":"0.0000","yes_ask":"1.0000","last_price":"0.0100","volume":null,"open_interest":null},{"market_id":"KXWCSCORE-26JUL11NORENG-NOR1ENG4","event_ticker":"KXWCSCORE-26JUL11NORENG","captured_at":"2026-07-11T23:47:54.855364","title":"Will the final score be England wins 4-1?","status":"finalized","result":"no","yes_bid":"0.0000","yes_ask":"1.0000","last_price":"0.0100","volume":null,"open_interest":null},{"market_id":"KXWCSCORE-26JUL11NORENG-NOR1ENG5","event_ticker":"KXWCSCORE-26JUL11NORENG","captured_at":"2026-07-11T23:47:54.855364","title":"Will the final score be England wins 5-1?","status":"finalized","result":"no","yes_bid":"0.0000","yes_ask":"1.0000","last_price":"0.0100","volume":null,"open_interest":null},{"market_id":"KXWCSCORE-26JUL11NORENG-NOR1ENG6","event_ticker":"KXWCSCORE-26JUL11NORENG","captured_at":"2026-07-11T23:47:54.855364","title":"Will the final score be England wins 6-1?","status":"finalized","result":"no","yes_bid":"0.0000","yes_ask":"1.0000","last_price":"0.0100","volume":null,"open_interest":null},{"market_id":"KXWCSCORE-26JUL11NORENG-NOR2ENG0","event_ticker":"KXWCSCORE-26JUL11NORENG","captured_at":"2026-07-11T23:47:54.855364","title":"Will the final score be Norway wins 2-0?","status":"finalized","result":"no","yes_bid":"0.0000","yes_ask":"1.0000","last_price":"0.0100","volume":null,"open_interest":null},{"market_id":"KXWCSCORE-26JUL11NORENG-NOR2ENG1","event_ticker":"KXWCSCORE-26JUL11NORENG","captured_at":"2026-07-11T23:47:54.855364","title":"Will the final score be Norway wins 2-1?","status":"finalized","result":"no","yes_bid":"0.0000","yes_ask":"1.0000","last_price":"0.0100","volume":null,"open_interest":null},{"market_id":"KXWCSCORE-26JUL11NORENG-NOR2ENG2","event_ticker":"KXWCSCORE-26JUL11NORENG","captured_at":"2026-07-11T23:47:54.855364","title":"Will the final score be Draw 2-2?","status":"finalized","result":"no","yes_bid":"0.0000","yes_ask":"1.0000","last_price":"0.0100","volume":null,"open_interest":null},{"market_id":"KXWCSCORE-26JUL11NORENG-NOR2ENG3","event_ticker":"KXWCSCORE-26JUL11NORENG","captured_at":"2026-07-11T23:47:54.855364","title":"Will the final score be England wins 3-2?","status":"finalized","result":"no","yes_bid":"0.0000","yes_ask":"1.0000","last_price":"0.0100","volume":null,"open_interest":null},{"market_id":"KXWCSCORE-26JUL11NORENG-NOR2ENG4","event_ticker":"KXWCSCORE-26JUL11NORENG","captured_at":"2026-07-11T23:47:54.855364","title":"Will the final score be England wins 4-2?","status":"finalized","result":"no","yes_bid":"0.0000","yes_ask":"1.0000","last_price":"0.0100","volume":null,"open_interest":null},{"market_id":"KXWCSCORE-26JUL11NORENG-NOR2ENG5","event_ticker":"KXWCSCORE-26JUL11NORENG","captured_at":"2026-07-11T23:47:54.855364","title":"Will the final score be England wins 5-2?","status":"finalized","result":"no","yes_bid":"0.0000","yes_ask":"1.0000","last_price":"0.0100","volume":null,"open_interest":null},{"market_id":"KXWCSCORE-26JUL11NORENG-NOR3ENG0","event_ticker":"KXWCSCORE-26JUL11NORENG","captured_at":"2026-07-11T23:47:54.855364","title":"Will the final score be Norway wins 3-0?","status":"finalized","result":"no","yes_bid":"0.0000","yes_ask":"1.0000","last_price":"0.0100","volume":null,"open_interest":null},{"market_id":"KXWCSCORE-26JUL11NORENG-NOR3ENG1","event_ticker":"KXWCSCORE-26JUL11NORENG","captured_at":"2026-07-11T23:47:54.855364","title":"Will the final score be Norway wins 3-1?","status":"finalized","result":"no","yes_bid":"0.0000","yes_ask":"1.0000","last_price":"0.0100","volume":null,"open_interest":null},{"market_id":"KXWCSCORE-26JUL11NORENG-NOR3ENG2","event_ticker":"KXWCSCORE-26JUL11NORENG","captured_at":"2026-07-11T23:47:54.855364","title":"Will the final score be Norway wins 3-2?","status":"finalized","result":"no","yes_bid":"0.0000","yes_ask":"1.0000","last_price":"0.0100","volume":null,"open_interest":null},{"market_id":"KXWCSCORE-26JUL11NORENG-NOR3ENG3","event_ticker":"KXWCSCORE-26JUL11NORENG","captured_at":"2026-07-11T23:47:54.855364","title":"Will the final score be Draw 3-3?","status":"finalized","result":"no","yes_bid":"0.0000","yes_ask":"1.0000","last_price":"0.0100","volume":null,"open_interest":null},{"market_id":"KXWCSCORE-26JUL11NORENG-NOR3ENG4","event_ticker":"KXWCSCORE-26JUL11NORENG","captured_at":"2026-07-11T23:47:54.855364","title":"Will the final score be England wins 4-3?","status":"finalized","result":"no","yes_bid":"0.0000","yes_ask":"1.0000","last_price":"0.0100","volume":null,"open_interest":null},{"market_id":"KXWCSCORE-26JUL11NORENG-NOR4ENG0","event_ticker":"KXWCSCORE-26JUL11NORENG","captured_at":"2026-07-11T23:47:54.855364","title":"Will the final score be Norway wins 4-0?","status":"finalized","result":"no","yes_bid":"0.0000","yes_ask":"1.0000","last_price":"0.0100","volume":null,"open_interest":null},{"market_id":"KXWCSCORE-26JUL11NORENG-NOR4ENG1","event_ticker":"KXWCSCORE-26JUL11NORENG","captured_at":"2026-07-11T23:47:54.855364","title":"Will the final score be Norway wins 4-1?","status":"finalized","result":"no","yes_bid":"0.0000","yes_ask":"1.0000","last_price":"0.0100","volume":null,"open_interest":null},{"market_id":"KXWCSCORE-26JUL11NORENG-NOR4ENG2","event_ticker":"KXWCSCORE-26JUL11NORENG","captured_at":"2026-07-11T23:47:54.855364","title":"Will the final score be Norway wins 4-2?","status":"finalized","result":"no","yes_bid":"0.0000","yes_ask":"1.0000","last_price":"0.0100","volume":null,"open_interest":null},{"market_id":"KXWCSCORE-26JUL11NORENG-NOR4ENG3","event_ticker":"KXWCSCORE-26JUL11NORENG","captured_at":"2026-07-11T23:47:54.855364","title":"Will the final score be Norway wins 4-3?","status":"finalized","result":"no","yes_bid":"0.0000","yes_ask":"1.0000","last_price":"0.0100","volume":null,"open_interest":null},{"market_id":"KXWCSPREAD-26JUL11NORENG-ENG2","event_ticker":"KXWCSPREAD-26JUL11NORENG","captured_at":"2026-07-11T23:47:54.855364","title":"England wins by more than 1.5 goals?","status":"finalized","result":"no","yes_bid":"0.0000","yes_ask":"1.0000","last_price":"0.0100","volume":null,"open_interest":null},{"market_id":"KXWCSPREAD-26JUL11NORENG-ENG3","event_ticker":"KXWCSPREAD-26JUL11NORENG","captured_at":"2026-07-11T23:47:54.855364","title":"England wins by more than 2.5 goals?","status":"finalized","result":"no","yes_bid":"0.0000","yes_ask":"1.0000","last_price":"0.0100","volume":null,"open_interest":null},{"market_id":"KXWCSPREAD-26JUL11NORENG-NOR2","event_ticker":"KXWCSPREAD-26JUL11NORENG","captured_at":"2026-07-11T23:47:54.855364","title":"Norway wins by more than 1.5 goals?","status":"finalized","result":"no","yes_bid":"0.0000","yes_ask":"1.0000","last_price":"0.0100","volume":null,"open_interest":null},{"market_id":"KXWCSPREAD-26JUL11NORENG-NOR3","event_ticker":"KXWCSPREAD-26JUL11NORENG","captured_at":"2026-07-11T23:47:54.855364","title":"Norway wins by more than 2.5 goals?","status":"finalized","result":"no","yes_bid":"0.0000","yes_ask":"1.0000","last_price":"0.0100","volume":null,"open_interest":null},{"market_id":"KXWCTOTAL-26JUL11NORENG-1","event_ticker":"KXWCTOTAL-26JUL11NORENG","captured_at":"2026-07-11T23:47:54.855364","title":"Will over 0.5 goals be scored?","status":"finalized","result":"yes","yes_bid":"0.0000","yes_ask":"1.0000","last_price":"0.9900","volume":null,"open_interest":null},{"market_id":"KXWCTOTAL-26JUL11NORENG-2","event_ticker":"KXWCTOTAL-26JUL11NORENG","captured_at":"2026-07-11T23:47:54.855364","title":"Will over 1.5 goals be scored?","status":"finalized","result":"yes","yes_bid":"0.0000","yes_ask":"1.0000","last_price":"0.9900","volume":null,"open_interest":null},{"market_id":"KXWCTOTAL-26JUL11NORENG-3","event_ticker":"KXWCTOTAL-26JUL11NORENG","captured_at":"2026-07-11T23:47:54.855364","title":"Will over 2.5 goals be scored?","status":"finalized","result":"no","yes_bid":"0.0000","yes_ask":"1.0000","last_price":"0.0100","volume":null,"open_interest":null},{"market_id":"KXWCTOTAL-26JUL11NORENG-4","event_ticker":"KXWCTOTAL-26JUL11NORENG","captured_at":"2026-07-11T23:47:54.855364","title":"Will over 3.5 goals be scored?","status":"finalized","result":"no","yes_bid":"0.0000","yes_ask":"1.0000","last_price":"0.0100","volume":null,"open_interest":null},{"market_id":"KXWCTOTAL-26JUL11NORENG-5","event_ticker":"KXWCTOTAL-26JUL11NORENG","captured_at":"2026-07-11T23:47:54.855364","title":"Will over 4.5 goals be scored?","status":"finalized","result":"no","yes_bid":"0.0000","yes_ask":"1.0000","last_price":"0.0100","volume":null,"open_interest":null},{"market_id":"KXWCTOTAL-26JUL11NORENG-6","event_ticker":"KXWCTOTAL-26JUL11NORENG","captured_at":"2026-07-11T23:47:54.855364","title":"Will over 5.5 goals be scored?","status":"finalized","result":"no","yes_bid":"0.0000","yes_ask":"1.0000","last_price":"0.0100","volume":null,"open_interest":null},{"market_id":"KXWCTOTAL-26JUL11NORENG-7","event_ticker":"KXWCTOTAL-26JUL11NORENG","captured_at":"2026-07-11T23:47:54.855364","title":"Will over 6.5 goals be scored?","status":"finalized","result":"no","yes_bid":"0.0000","yes_ask":"1.0000","last_price":"0.0100","volume":null,"open_interest":null}],"last_readings":[{"market_id":"KXWCMOV-26JUL11NORENG-ENGET","yes_price":0.995,"model_probability":0.1502,"edge":-0.8448,"read_at":"2026-07-11T23:59:55.303974"},{"market_id":"KXWCMOV-26JUL11NORENG-ENGPEN","yes_price":0.01,"model_probability":0.1359,"edge":0.12589999999999998,"read_at":"2026-07-11T23:59:55.302252"},{"market_id":"KXWCMOV-26JUL11NORENG-NORET","yes_price":0.01,"model_probability":0.1195,"edge":0.1095,"read_at":"2026-07-11T23:59:55.300457"},{"market_id":"KXWCMOV-26JUL11NORENG-NORPEN","yes_price":0.01,"model_probability":0.1388,"edge":0.1288,"read_at":"2026-07-11T23:59:55.297877"},{"market_id":"KXWCADVANCE-26JUL11NORENG-ENG","yes_price":0.995,"model_probability":0.5634,"edge":-0.4316,"read_at":"2026-07-11T23:48:25.780477"},{"market_id":"KXWCADVANCE-26JUL11NORENG-NOR","yes_price":0.01,"model_probability":0.4406,"edge":0.4306,"read_at":"2026-07-11T23:48:25.778907"},{"market_id":"KXWCMOV-26JUL11NORENG-ENGREG","yes_price":0.01,"model_probability":0.4731,"edge":0.4631,"read_at":"2026-07-11T23:09:56.300934"},{"market_id":"KXWCMOV-26JUL11NORENG-NORREG","yes_price":0.01,"model_probability":0.2825,"edge":0.27249999999999996,"read_at":"2026-07-11T23:09:56.294074"},{"market_id":"KXWCSCORE-26JUL11NORENG-NOR0ENG1","yes_price":0.01,"model_probability":0.0379,"edge":0.0279,"read_at":"2026-07-11T23:09:56.292650"},{"market_id":"KXWCSCORE-26JUL11NORENG-NOR0ENG2","yes_price":0.01,"model_probability":0.0385,"edge":0.028499999999999998,"read_at":"2026-07-11T23:09:56.291388"},{"market_id":"KXWCSCORE-26JUL11NORENG-NOR0ENG3","yes_price":0.01,"model_probability":0.0243,"edge":0.014299999999999998,"read_at":"2026-07-11T23:09:56.290130"},{"market_id":"KXWCSCORE-26JUL11NORENG-NOR0ENG4","yes_price":0.01,"model_probability":0.0137,"edge":0.0037,"read_at":"2026-07-11T23:09:56.288926"},{"market_id":"KXWCSCORE-26JUL11NORENG-NOR0ENG5","yes_price":0.01,"model_probability":0.0071,"edge":-0.0029,"read_at":"2026-07-11T23:09:56.287638"},{"market_id":"KXWCSCORE-26JUL11NORENG-NOR1ENG0","yes_price":0.01,"model_probability":0.0356,"edge":0.025599999999999998,"read_at":"2026-07-11T23:09:56.285907"},{"market_id":"KXWCSCORE-26JUL11NORENG-NOR1ENG1","yes_price":0.995,"model_probability":0.4296,"edge":-0.5654,"read_at":"2026-07-11T23:09:56.284166"},{"market_id":"KXWCSCORE-26JUL11NORENG-NOR1ENG2","yes_price":0.01,"model_probability":0.074,"edge":0.064,"read_at":"2026-07-11T23:09:56.282600"},{"market_id":"KXWCSCORE-26JUL11NORENG-NOR1ENG3","yes_price":0.01,"model_probability":0.038,"edge":0.027999999999999997,"read_at":"2026-07-11T23:09:56.281100"},{"market_id":"KXWCSCORE-26JUL11NORENG-NOR1ENG4","yes_price":0.01,"model_probability":0.0191,"edge":0.009099999999999999,"read_at":"2026-07-11T23:09:56.279496"},{"market_id":"KXWCSCORE-26JUL11NORENG-NOR1ENG5","yes_price":0.01,"model_probability":0.0104,"edge":0.0003999999999999993,"read_at":"2026-07-11T23:09:56.278014"},{"market_id":"KXWCSCORE-26JUL11NORENG-NOR1ENG6","yes_price":0.01,"model_probability":null,"edge":null,"read_at":"2026-07-11T23:09:56.276446"},{"market_id":"KXWCSCORE-26JUL11NORENG-NOR2ENG0","yes_price":0.01,"model_probability":0.0266,"edge":0.016599999999999997,"read_at":"2026-07-11T23:09:56.274629"},{"market_id":"KXWCSCORE-26JUL11NORENG-NOR2ENG1","yes_price":0.01,"model_probability":0.0502,"edge":0.0402,"read_at":"2026-07-11T23:09:56.273013"},{"market_id":"KXWCSCORE-26JUL11NORENG-NOR2ENG2","yes_price":0.01,"model_probability":0.0447,"edge":0.034699999999999995,"read_at":"2026-07-11T23:09:56.271675"},{"market_id":"KXWCSCORE-26JUL11NORENG-NOR2ENG3","yes_price":0.01,"model_probability":0.0284,"edge":0.0184,"read_at":"2026-07-11T23:09:56.270377"},{"market_id":"KXWCSCORE-26JUL11NORENG-NOR2ENG4","yes_price":0.01,"model_probability":0.0152,"edge":0.0052,"read_at":"2026-07-11T23:09:56.268979"},{"market_id":"KXWCSCORE-26JUL11NORENG-NOR2ENG5","yes_price":0.01,"model_probability":0.008,"edge":-0.002,"read_at":"2026-07-11T23:09:56.267479"},{"market_id":"KXWCSCORE-26JUL11NORENG-NOR3ENG0","yes_price":0.01,"model_probability":0.0182,"edge":0.0082,"read_at":"2026-07-11T23:09:56.265591"},{"market_id":"KXWCSCORE-26JUL11NORENG-NOR3ENG1","yes_price":0.01,"model_probability":0.0276,"edge":0.017599999999999998,"read_at":"2026-07-11T23:09:56.262579"},{"market_id":"KXWCSCORE-26JUL11NORENG-NOR3ENG2","yes_price":0.01,"model_probability":0.0275,"edge":0.0175,"read_at":"2026-07-11T23:09:56.260929"},{"market_id":"KXWCSCORE-26JUL11NORENG-NOR3ENG3","yes_price":0.01,"model_probability":0.0178,"edge":0.0078,"read_at":"2026-07-11T23:09:56.258413"},{"market_id":"KXWCSCORE-26JUL11NORENG-NOR3ENG4","yes_price":0.01,"model_probability":0.011,"edge":0.0009999999999999992,"read_at":"2026-07-11T23:09:56.256529"},{"market_id":"KXWCSCORE-26JUL11NORENG-NOR4ENG0","yes_price":0.01,"model_probability":0.0098,"edge":-0.00020000000000000052,"read_at":"2026-07-11T23:09:56.254614"},{"market_id":"KXWCSCORE-26JUL11NORENG-NOR4ENG1","yes_price":0.01,"model_probability":0.0158,"edge":0.005800000000000001,"read_at":"2026-07-11T23:09:56.252895"},{"market_id":"KXWCSCORE-26JUL11NORENG-NOR4ENG2","yes_price":0.01,"model_probability":0.0137,"edge":0.0037,"read_at":"2026-07-11T23:09:56.250293"},{"market_id":"KXWCSCORE-26JUL11NORENG-NOR4ENG3","yes_price":0.01,"model_probability":0.0095,"edge":-0.0005000000000000004,"read_at":"2026-07-11T23:09:56.247638"},{"market_id":"KXWCGAME-26JUL11NORENG-ENG","yes_price":0.01,"model_probability":0.2853,"edge":0.2753,"read_at":"2026-07-11T23:03:57.802250"},{"market_id":"KXWCGAME-26JUL11NORENG-NOR","yes_price":0.01,"model_probability":0.2143,"edge":0.20429999999999998,"read_at":"2026-07-11T23:03:57.800847"},{"market_id":"KXWCGAME-26JUL11NORENG-TIE","yes_price":0.995,"model_probability":0.5043,"edge":-0.4907,"read_at":"2026-07-11T23:03:57.799342"},{"market_id":"KXWCSPREAD-26JUL11NORENG-ENG2","yes_price":0.01,"model_probability":0.2209,"edge":0.2109,"read_at":"2026-07-11T22:59:57.695856"},{"market_id":"KXWCSPREAD-26JUL11NORENG-ENG3","yes_price":0.01,"model_probability":0.0878,"edge":0.07780000000000001,"read_at":"2026-07-11T22:59:57.694119"},{"market_id":"KXWCSPREAD-26JUL11NORENG-NOR2","yes_price":0.01,"model_probability":0.1321,"edge":0.1221,"read_at":"2026-07-11T22:59:57.692388"},{"market_id":"KXWCSPREAD-26JUL11NORENG-NOR3","yes_price":0.01,"model_probability":0.0504,"edge":0.0404,"read_at":"2026-07-11T22:59:57.690727"},{"market_id":"KXWCTOTAL-26JUL11NORENG-2","yes_price":0.995,"model_probability":0.9183,"edge":-0.07669999999999999,"read_at":"2026-07-11T22:59:57.687189"},{"market_id":"KXWCTOTAL-26JUL11NORENG-3","yes_price":0.06,"model_probability":0.74,"edge":0.6799999999999999,"read_at":"2026-07-11T22:59:57.685103"},{"market_id":"KXWCTOTAL-26JUL11NORENG-4","yes_price":0.01,"model_probability":0.4763,"edge":0.4663,"read_at":"2026-07-11T22:59:57.681848"},{"market_id":"KXWCTOTAL-26JUL11NORENG-5","yes_price":0.01,"model_probability":0.2595,"edge":0.2495,"read_at":"2026-07-11T22:59:57.678792"},{"market_id":"KXWCTOTAL-26JUL11NORENG-6","yes_price":0.01,"model_probability":0.1166,"edge":0.1066,"read_at":"2026-07-11T22:59:57.670621"},{"market_id":"KXWCFTTS-26JUL11NORENG-ENG","yes_price":0.01,"model_probability":0.5476,"edge":0.5376,"read_at":"2026-07-11T21:59:58.679913"},{"market_id":"KXWCFTTS-26JUL11NORENG-NONE","yes_price":0.01,"model_probability":0.0378,"edge":0.0278,"read_at":"2026-07-11T21:59:58.678418"},{"market_id":"KXWCFTTS-26JUL11NORENG-NOR","yes_price":0.995,"model_probability":0.4266,"edge":-0.5684,"read_at":"2026-07-11T21:59:58.676974"},{"market_id":"KXWCSCORE-26JUL11NORENG-NOR0ENG0","yes_price":0.01,"model_probability":0.0414,"edge":0.0314,"read_at":"2026-07-11T21:59:58.662735"},{"market_id":"KXWCBTTS-26JUL11NORENG-BTTS","yes_price":0.995,"model_probability":0.6617,"edge":-0.33330000000000004,"read_at":"2026-07-11T21:59:58.615114"},{"market_id":"KXWCTOTAL-26JUL11NORENG-1","yes_price":0.995,"model_probability":0.9626,"edge":-0.032399999999999984,"read_at":"2026-07-11T21:49:58.915392"}],"generated_at":"2026-07-12T03:05:01.861714+00:00"}